AUTHORS.rst
LICENSE.txt
README.md
setup.cfg
setup.py
src/i3_instant_layout/__init__.py
src/i3_instant_layout/layouts.py
src/i3_instant_layout/main.py
src/i3_instant_layout.egg-info/PKG-INFO
src/i3_instant_layout.egg-info/SOURCES.txt
src/i3_instant_layout.egg-info/dependency_links.txt
src/i3_instant_layout.egg-info/entry_points.txt
src/i3_instant_layout.egg-info/not-zip-safe
src/i3_instant_layout.egg-info/requires.txt
src/i3_instant_layout.egg-info/top_level.txt