Metadata-Version: 2.1
Name: i3-instant-layout
Version: 0.1.13
Summary: Automatic 'list based' layouts for the i3 window manager
Home-page: https://github.com/TyberiusPrime/i3-instant-layout
Author: Florian Finkernagel
Author-email: tyberius_prime@coonabibba.de
License: mit
Platform: Linux
Classifier: Development Status :: 4 - Beta
Classifier: Programming Language :: Python
Requires-Python: >=3.6
License-File: LICENSE.txt
License-File: AUTHORS.rst
Requires-Dist: i3ipc>=2.2.1
Provides-Extra: testing
Requires-Dist: pytest; extra == "testing"
Requires-Dist: pytest-cov; extra == "testing"
